fastapi_healthcheck_uri/__init__.py
fastapi_healthcheck_uri/service.py
fastapi_healthcheck_uri-0.1.0.dist-info/LICENSE
fastapi_healthcheck_uri-0.1.0.dist-info/WHEEL
fastapi_healthcheck_uri-0.1.0.dist-info/METADATA
fastapi_healthcheck_uri-0.1.0.dist-info/RECORD
