Metadata-Version: 2.1
Name: fastapi-healthcheck-uri
Version: 0.1.0
Summary: A module to have a FastAPI HealthCheck reach out to a URI to validate external service health.
Home-page: https://github.com/jtom38/fastapi_healthcheck_uri
License: MIT
Author: James Tombleson
Author-email: luther38@gmail.com
Requires-Python: >=3.9,<4.0
Classifier: Development Status :: 3 - Alpha
Classifier: Framework :: FastAPI
Classifier: License :: OSI Approved :: MIT License
Classifier: Programming Language :: Python :: 3
Classifier: Programming Language :: Python :: 3.10
Classifier: Programming Language :: Python :: 3.9
Requires-Dist: fastapi-healthcheck (>=0.2.2,<0.3.0)
Requires-Dist: requests (>=2.26.0,<3.0.0)
Project-URL: Repository, https://github.com/jtom38/fastapi_healthcheck_uri
